csdigit/__init__.py
csdigit/cli.py
csdigit/csd.py
csdigit/lcsre.py
csdigit-0.1.dist-info/licenses/LICENSE.txt
pycsd/README
pycsd/__init__.py
pycsd/csd_orig.py
pycsd/from_csd
pycsd/run_tests.py
pycsd/to_csd
pycsd/csd/__init__.py
pycsd/csd/csd.py
pycsd/dev/csd_numbers.py
pycsd/test/__init__.py
pycsd/test/decimal_tests.py
pycsd/test/test_csd_decimals.py
pycsd/test/test_csd_integers.py
pycsd/test/test_to_and_fro_10bits.py
csdigit-0.1.dist-info/METADATA
csdigit-0.1.dist-info/WHEEL
csdigit-0.1.dist-info/top_level.txt
csdigit-0.1.dist-info/RECORD
